labda_accelerometers/__init__.py
labda_accelerometers/py.typed
labda_accelerometers/utils.py
labda_accelerometers/metrics/__init__.py
labda_accelerometers/metrics/counts.py
labda_accelerometers/metrics/enmo.py
labda_accelerometers/metrics/mad.py
labda_accelerometers/metrics/metrics.py
labda_accelerometers/preprocessing/__init__.py
labda_accelerometers/preprocessing/calibration.py
labda_accelerometers/preprocessing/wear.py
labda_accelerometers-0.1.2.dist-info/METADATA
labda_accelerometers-0.1.2.dist-info/WHEEL
labda_accelerometers-0.1.2.dist-info/licenses/LICENSE
labda_accelerometers-0.1.2.dist-info/RECORD
