Metadata-Version: 2.4
Name: labda-accelerometers
Version: 0.1.2
Summary: A package designed to process data from movement sensors – accelerometers.
Project-URL: Homepage, https://github.com/josefheidler/labda-accelerometers
Project-URL: Documentation, https://labda.josefheidler.cz/accelerometers
Project-URL: Source, https://github.com/josefheidler/labda-accelerometers
Project-URL: Changelog, https://labda.josefheidler.cz/accelerometers/changelog
Author-email: Josef Heidler <jheidler@health.sdu.dk>
License-Expression: BSD-3-Clause
License-File: LICENSE
Keywords: accelerometers,movement-behavior,physical-activity,sensors
Classifier: Intended Audience :: Education
Classifier: Intended Audience :: Science/Research
Classifier: Operating System :: OS Independent
Classifier: Programming Language :: Python
Classifier: Programming Language :: Python :: 3
Classifier: Programming Language :: Python :: 3 :: Only
Classifier: Programming Language :: Python :: 3.11
Classifier: Programming Language :: Python :: 3.12
Classifier: Topic :: Scientific/Engineering
Requires-Python: >=3.11
Requires-Dist: agcounts>=0.2.6
Requires-Dist: numba>=0.61.2
Requires-Dist: pandas>=2.2.3
Requires-Dist: resampy>=0.4.3
Requires-Dist: scikit-digital-health>=0.17.9
